demogeo/__init__.py
demogeo/common.py
demogeo/demogeo.py
demogeo-0.0.1.dist-info/LICENSE
demogeo-0.0.1.dist-info/METADATA
demogeo-0.0.1.dist-info/WHEEL
demogeo-0.0.1.dist-info/entry_points.txt
demogeo-0.0.1.dist-info/top_level.txt
demogeo-0.0.1.dist-info/RECORD
