Metadata-Version: 2.1
Name: demogeo
Version: 0.0.1
Summary: Python Package created for geospatial analysis using cookiecutter (for demo only)
Author-email: Subesh Bhattarai <subsonicu571@gmail.com>
License: MIT License
Project-URL: Homepage, https://github.com/Sub-esh/demogeo
Keywords: demogeo
Classifier: Intended Audience :: Developers
Classifier: License :: OSI Approved :: MIT License
Classifier: Natural Language :: English
Classifier: Programming Language :: Python :: 3.8
Classifier: Programming Language :: Python :: 3.9
Classifier: Programming Language :: Python :: 3.10
Classifier: Programming Language :: Python :: 3.11
Classifier: Programming Language :: Python :: 3.12
Requires-Python: >=3.8
License-File: LICENSE
Requires-Dist: numpy
Provides-Extra: all
Requires-Dist: demogeo[extra] ; extra == 'all'
Provides-Extra: extra
Requires-Dist: pandas ; extra == 'extra'
